pydivsufsort/__init__.py
pydivsufsort/divsufsort.py
pydivsufsort/dll.py
pydivsufsort/libdivsufsort.so.3.0.1
pydivsufsort/libdivsufsort64.so.3.0.1
pydivsufsort/stringalg.cpython-314t-aarch64-linux-gnu.so
pydivsufsort/wonderstring.py
pydivsufsort.libs/libgomp-a49a47f9.so.1.0.0
pydivsufsort-0.0.20.dist-info/METADATA
pydivsufsort-0.0.20.dist-info/WHEEL
pydivsufsort-0.0.20.dist-info/top_level.txt
pydivsufsort-0.0.20.dist-info/RECORD
pydivsufsort-0.0.20.dist-info/licenses/LICENSE
pydivsufsort-0.0.20.dist-info/sboms/auditwheel.cdx.json
