Metadata-Version: 2.4
Name: pydivsufsort
Version: 0.0.20
Summary: String algorithms
Home-page: https://github.com/louisabraham/pydivsufsort
Author: Louis Abraham
Author-email: louis.abraham@yahoo.fr
License: MIT
Requires-Python: >=3.9
License-File: LICENSE
Requires-Dist: wheel
Requires-Dist: numpy
Dynamic: author
Dynamic: author-email
Dynamic: description
Dynamic: description-content-type
Dynamic: home-page
Dynamic: license
Dynamic: license-file
Dynamic: requires-dist
Dynamic: requires-python
Dynamic: summary
